tests/__init__.py
tests/test_simple.py
tests/test_query/__init__.py
tests/test_query/test_SGQuery.py
thanetwffapi/Time.py
thanetwffapi/__init__.py
thanetwffapi/simple.py
thanetwffapi/dev/__init__.py
thanetwffapi/dev/dev.py
thanetwffapi/query/SGQuery.py
thanetwffapi/query/__init__.py
thanetwffapi/query/SG_GF/A02_GF.csv
thanetwffapi/query/SG_GF/A07_GF.csv
thanetwffapi/query/SG_GF/E06_GF.csv
thanetwffapi/query/SG_GF/F07_GF.csv
thanetwffapi/query/SG_GF/G03_GF.csv
thanetwffapi/query/SG_GF/__init__.py
thanetwffapi-0.0.24.dist-info/LICENSE
thanetwffapi-0.0.24.dist-info/METADATA
thanetwffapi-0.0.24.dist-info/WHEEL
thanetwffapi-0.0.24.dist-info/top_level.txt
thanetwffapi-0.0.24.dist-info/RECORD
