Metadata-Version: 2.1
Name: thanetwffapi
Version: 0.0.24
Summary: API for Thanet offshore wind farm foundation data
Home-page: UNKNOWN
License: UNKNOWN
Platform: UNKNOWN
Classifier: License :: OSI Approved :: MIT License
Classifier: Programming Language :: Python :: 3
